<annotation>
	<folder>images_for_training</folder>
	<filename>img9.png</filename>
	<path>/home/matrix/WORK/PROJECTS/SortWarrior/soft_and_firm/rpi_main/lib/vision/model_training/images_for_training/img9.png</path>
	<source>
		<database>Unknown</database>
	</source>
	<size>
		<width>1964</width>
		<height>1160</height>
		<depth>3</depth>
	</size>
	<segmented>0</segmented>
	<object>
		<name>red_puck</name>
		<pose>Unspecified</pose>
		<truncated>0</truncated>
		<difficult>0</difficult>
		<bndbox>
			<xmin>742</xmin>
			<ymin>332</ymin>
			<xmax>790</xmax>
			<ymax>380</ymax>
		</bndbox>
	</object>
	<object>
		<name>red_puck</name>
		<pose>Unspecified</pose>
		<truncated>0</truncated>
		<difficult>0</difficult>
		<bndbox>
			<xmin>216</xmin>
			<ymin>514</ymin>
			<xmax>276</xmax>
			<ymax>567</ymax>
		</bndbox>
	</object>
	<object>
		<name>red_puck</name>
		<pose>Unspecified</pose>
		<truncated>0</truncated>
		<difficult>0</difficult>
		<bndbox>
			<xmin>205</xmin>
			<ymin>599</ymin>
			<xmax>265</xmax>
			<ymax>657</ymax>
		</bndbox>
	</object>
	<object>
		<name>red_puck</name>
		<pose>Unspecified</pose>
		<truncated>0</truncated>
		<difficult>0</difficult>
		<bndbox>
			<xmin>155</xmin>
			<ymin>771</ymin>
			<xmax>221</xmax>
			<ymax>838</ymax>
		</bndbox>
	</object>
	<object>
		<name>blue_base</name>
		<pose>Unspecified</pose>
		<truncated>0</truncated>
		<difficult>0</difficult>
		<bndbox>
			<xmin>894</xmin>
			<ymin>147</ymin>
			<xmax>1882</xmax>
			<ymax>614</ymax>
		</bndbox>
	</object>
</annotation>
